<Properties StartupConfiguration="{FC588EBC-8499-46DC-2C88-3411EA4227F4}|">
  <MonoDevelop.Ide.Workbench ActiveDocument="Assets/Scripts/MainMenuLogic.cs">
    <Files>
      <File FileName="Assets/Scripts/MainMenuLogic.cs" Line="1" Column="1" />
      <File FileName="Assets/Scripts/SettingsMenuLogic.cs" Line="19" Column="1" />
    </Files>
    <Pads>
      <Pad Id="ProjectPad">
        <State name="__root__">
          <Node name="UFO Game" expanded="True">
            <Node name="Assets" expanded="True">
              <Node name="Scripts" expanded="True">
                <Node name="MainMenuLogic.cs" selected="True" />
              </Node>
            </Node>
          </Node>
        </State>
      </Pad>
    </Pads>
  </MonoDevelop.Ide.Workbench>
  <MonoDevelop.Ide.DebuggingService.PinnedWatches />
  <MonoDevelop.Ide.Workspace ActiveConfiguration="Debug" />
  <MonoDevelop.Ide.ItemProperties.Assembly-CSharp PreferredExecutionTarget="75bf59bd-4734-46e3-b93a-24e98bca5c24" />
  <MonoDevelop.Ide.DebuggingService.Breakpoints>
    <BreakpointStore />
  </MonoDevelop.Ide.DebuggingService.Breakpoints>
  <MultiItemStartupConfigurations />
</Properties>